LICENSE
README.md
pyproject.toml
pytest_relative_order.py
setup.cfg
setup.py
pytest_relative_order.egg-info/PKG-INFO
pytest_relative_order.egg-info/SOURCES.txt
pytest_relative_order.egg-info/dependency_links.txt
pytest_relative_order.egg-info/entry_points.txt
pytest_relative_order.egg-info/requires.txt
pytest_relative_order.egg-info/top_level.txt